truedata_ws/__init__.py
truedata_ws/__main__.py
truedata_ws/websocket/TD.py
truedata_ws/websocket/TD_chain.py
truedata_ws/websocket/TD_hist.py
truedata_ws/websocket/TD_live.py
truedata_ws/websocket/__init__.py
truedata_ws/websocket/base_tests.py
truedata_ws/websocket/client_tests.py
truedata_ws/websocket/defaults.py
truedata_ws/websocket/internal_tests.py
truedata_ws/websocket/support.py
truedata_ws-5.0.11.dist-info/LICENSE
truedata_ws-5.0.11.dist-info/METADATA
truedata_ws-5.0.11.dist-info/WHEEL
truedata_ws-5.0.11.dist-info/top_level.txt
truedata_ws-5.0.11.dist-info/RECORD
