Metadata-Version: 2.1
Name: truedata-ws
Version: 5.0.11
Summary: Truedata's Official Python Package
Home-page: https://github.com/kapilmar/truedata-ws
Author: Kapil Marwaha
Author-email: kapil@truedata.in
License: UNKNOWN
Platform: UNKNOWN
Classifier: Programming Language :: Python :: 3.7
Classifier: Programming Language :: Python :: 3.8
Classifier: License :: OSI Approved :: GNU General Public License v3 (GPLv3)
Classifier: Operating System :: OS Independent
Requires-Python: >=3.7
